hive_metasploit/__init__.py
hive_metasploit/cli.py
hive_metasploit/color.py
hive_metasploit-0.0.1a2.dist-info/METADATA
hive_metasploit-0.0.1a2.dist-info/WHEEL
hive_metasploit-0.0.1a2.dist-info/entry_points.txt
hive_metasploit-0.0.1a2.dist-info/top_level.txt
hive_metasploit-0.0.1a2.dist-info/RECORD
