Metadata-Version: 2.1
Name: hive-metasploit
Version: 0.0.1a2
Summary: Hive Metasploit connector
Home-page: https://hive-metasploit.github.io/
Author: Vladimir Ivanov
Author-email: ivanov.vladimir.mail@gmail.com
License: UNKNOWN
Platform: UNKNOWN
Classifier: Development Status :: 4 - Beta
Classifier: Environment :: Console
Classifier: Intended Audience :: Education
Classifier: License :: OSI Approved :: MIT License
Classifier: Natural Language :: English
Classifier: Operating System :: MacOS
Classifier: Operating System :: Microsoft :: Windows
Classifier: Operating System :: POSIX :: Linux
Classifier: Programming Language :: Python :: 3 :: Only
Classifier: Programming Language :: Python :: 3.6
Classifier: Programming Language :: Python :: 3.7
Classifier: Programming Language :: Python :: 3.8
Classifier: Programming Language :: Python :: 3.9
Classifier: Programming Language :: Python :: 3.10
Classifier: Topic :: Education
Classifier: Topic :: Security
Requires-Python: >=3.6
Requires-Dist: hive-library
Requires-Dist: marshmallow
Requires-Dist: colorama
Requires-Dist: libmsf
